coils/Averager.py
coils/MapSock.py
coils/RateTicker.py
coils/Ring.py
coils/SocketTalk.py
coils/SortedList.py
coils/String.py
coils/Timer.py
coils/UserInput.py
coils/__init__.py
coils/version.py
coils-2.0.2.dist-info/LICENSE
coils-2.0.2.dist-info/METADATA
coils-2.0.2.dist-info/WHEEL
coils-2.0.2.dist-info/top_level.txt
coils-2.0.2.dist-info/RECORD
