Metadata-Version: 2.1
Name: coils
Version: 2.0.2
Summary: A tiny library of generic codes written in 100% pure Python.
Home-page: http://vmlaker.github.io/coils
Author: Velimir Mlaker
Author-email: velimir.mlaker@gmail.com
License: MIT
Platform: UNKNOWN
Classifier: Development Status :: 5 - Production/Stable
Classifier: Intended Audience :: Developers
Classifier: License :: Freeware
Classifier: Operating System :: OS Independent
Classifier: Programming Language :: Python
Classifier: Programming Language :: Python :: 3
Classifier: Topic :: Software Development :: Libraries :: Python Modules
